bomiot/__init__.py
bomiot/__version__.py
bomiot/cmd/__init__.py
bomiot/cmd/changeapps.py
bomiot/cmd/cmd.py
bomiot/cmd/copyfile.py
bomiot/cmd/create_key.py
bomiot/cmd/createapp.py
bomiot/cmd/deploy.py
bomiot/cmd/extends/__init__.py
bomiot/cmd/extends/admin.py
bomiot/cmd/extends/apps.py
bomiot/cmd/extends/filter.py
bomiot/cmd/extends/migrations/__init__.py
bomiot/cmd/extends/models.py
bomiot/cmd/extends/serializers.py
bomiot/cmd/extends/tests.py
bomiot/cmd/extends/urls.py
bomiot/cmd/extends/views.py
bomiot/cmd/file/.gitignore
bomiot/cmd/file/__init__.py
bomiot/cmd/file/__version__.py
bomiot/cmd/file/api.py
bomiot/cmd/file/bomiotconf.ini
bomiot/cmd/file/example.py
bomiot/cmd/file/files.py
bomiot/cmd/file/LICENSE
bomiot/cmd/file/pyproject.toml
bomiot/cmd/file/README.md
bomiot/cmd/file/receiver.py
bomiot/cmd/file/server.py
bomiot/cmd/file/setup.ini
bomiot/cmd/file/supervisor.conf
bomiot/cmd/file/websocket.py
bomiot/cmd/init.py
bomiot/cmd/initadmin.py
bomiot/cmd/initpwd.py
bomiot/cmd/killport.py
bomiot/cmd/market.py
bomiot/cmd/migrate.py
bomiot/cmd/plugins.py
bomiot/cmd/project.py
bomiot/server/.gitignore
bomiot/server/__init__.py
bomiot/server/bomiot_static/__init__.py
bomiot/server/bomiotconf.ini
bomiot/server/core/__init__.py
bomiot/server/core/admin.py
bomiot/server/core/apps.py
bomiot/server/core/auth.py
bomiot/server/core/client.py
bomiot/server/core/field.py
bomiot/server/core/filter.py
bomiot/server/core/handler.py
bomiot/server/core/jwt_auth.py
bomiot/server/core/message.py
bomiot/server/core/middlewares.py
bomiot/server/core/migrations/0001_initial.py
bomiot/server/core/migrations/0002_delete_pypi.py
bomiot/server/core/migrations/0003_asndetail_dndetail_stockbin_delete_api_asn_project_and_more.py
bomiot/server/core/migrations/0004_remove_team_project.py
bomiot/server/core/migrations/__init__.py
bomiot/server/core/models.py
bomiot/server/core/my_exceptions.py
bomiot/server/core/observer.py
bomiot/server/core/page.py
bomiot/server/core/permission.py
bomiot-1.1.22.dist-info/entry_points.txt
bomiot-1.1.22.dist-info/LICENSE
bomiot-1.1.22.dist-info/METADATA
bomiot-1.1.22.dist-info/notice.py
bomiot-1.1.22.dist-info/WHEEL
bomiot-1.1.22.dist-info/RECORD
